fastkaggle/__init__.py
fastkaggle/_modidx.py
fastkaggle/_nbdev.py
fastkaggle/core.py
fastkaggle-0.0.8.dist-info/LICENSE
fastkaggle-0.0.8.dist-info/METADATA
fastkaggle-0.0.8.dist-info/WHEEL
fastkaggle-0.0.8.dist-info/entry_points.txt
fastkaggle-0.0.8.dist-info/top_level.txt
fastkaggle-0.0.8.dist-info/RECORD
