Metadata-Version: 2.1
Name: fastkaggle
Version: 0.0.8
Summary: Kaggling for fast kagglers!
Home-page: https://github.com/fastai/fastkaggle/tree/master/
Author: Jeremy Howard
Author-email: info@fast.ai
License: Apache Software License 2.0
Keywords: machine-learning kaggle fastai nbdev
Platform: UNKNOWN
Classifier: Development Status :: 3 - Alpha
Classifier: Intended Audience :: Developers
Classifier: Natural Language :: English
Classifier: Programming Language :: Python :: 3.7
Classifier: Programming Language :: Python :: 3.8
Classifier: License :: OSI Approved :: Apache Software License
Requires-Python: >=3.7
License-File: LICENSE
Requires-Dist: fastcore (>=1.4.5)
Requires-Dist: kaggle
Provides-Extra: dev
